MANIFEST.in
README.rst
setup.cfg
setup.py
cfg/nginx
cfg/supervisord
cfg/uwsgi
vaultier/manage.py
vaultier/accounts/__init__.py
vaultier/accounts/api.py
vaultier/accounts/models.py
vaultier/accounts/serializers.py
vaultier/accounts/tasks.py
vaultier/accounts/business/__init__.py
vaultier/accounts/business/authentication.py
vaultier/accounts/business/fields.py
vaultier/accounts/business/mailer.py
vaultier/accounts/business/managers.py
vaultier/accounts/business/permissions.py
vaultier/accounts/migrations/0001_initial.py
vaultier/accounts/migrations/0002_auto__add_field_member_workspace.py
vaultier/accounts/migrations/__init__.py
vaultier/accounts/templates/mailer/lostkey.html
vaultier/accounts/templates/mailer/lostkey.txt
vaultier/accounts/tests/__init__.py
vaultier/accounts/tests/api.py
vaultier/accounts/tests/lostkey.py
vaultier/accounts/tests/member.py
vaultier/accounts/tests/user.py
vaultier/acls/__init__.py
vaultier/acls/api.py
vaultier/acls/models.py
vaultier/acls/serializers.py
vaultier/acls/business/__init__.py
vaultier/acls/business/fields.py
vaultier/acls/business/mailer.py
vaultier/acls/business/managers.py
vaultier/acls/business/permissions.py
vaultier/acls/business/perms/__init__.py
vaultier/acls/business/perms/check.py
vaultier/acls/business/perms/materializer.py
vaultier/acls/business/perms/signals.py
vaultier/acls/business/perms/strategy.py
vaultier/acls/management/__init__.py
vaultier/acls/management/utils.py
vaultier/acls/management/commands/__init__.py
vaultier/acls/management/commands/rematerializeacl.py
vaultier/acls/migrations/0001_initial.py
vaultier/acls/migrations/__init__.py
vaultier/acls/templates/mailer/granted_access.html
vaultier/acls/templates/mailer/granted_access.txt
vaultier/acls/tests/__init__.py
vaultier/acls/tests/acl.py
vaultier/acls/tests/api.py
vaultier/acls/tests/role.py
vaultier/cards/__init__.py
vaultier/cards/api.py
vaultier/cards/models.py
vaultier/cards/serializers.py
vaultier/cards/business/__init__.py
walt.egg-info/PKG-INFO
walt.egg-info/SOURCES.txt
walt.egg-info/dependency_links.txt
walt.egg-info/entry_points.txt
walt.egg-info/requires.txt
walt.egg-info/top_level.txt
walt.egg-info/zip-safe